{
  "runId": "f6f4ee07-8e8b-44b5-b375-733d663da25c",
  "skill": "comet-classic",
  "skillVersion": "1",
  "skillHash": "e211dc93b4bbc218965022f6d64f54a26e2240bd45b8bf6e1321ceb96775a3a3",
  "orchestration": "deterministic",
  "currentStep": "completed",
  "iteration": 7,
  "pending": null,
  "pendingRef": ".comet/pending-action.json",
  "trajectoryRef": ".comet/trajectory.jsonl",
  "contextRef": ".comet/context.md",
  "artifactsRef": ".comet/artifacts.json",
  "checkpointRef": ".comet/checkpoint.json",
  "status": "completed",
  "retries": {}
}